pyarti/__init__.py
pyarti/__main__.py
pyarti/py.typed
pyarti/pyarti.cpython-39-x86_64-linux-gnu.so
pyarti/pyarti.pyi
pyarti-0.0.2.dist-info/LICENSE
pyarti-0.0.2.dist-info/METADATA
pyarti-0.0.2.dist-info/WHEEL
pyarti-0.0.2.dist-info/top_level.txt
pyarti-0.0.2.dist-info/RECORD
pyarti.libs/libssl-2a9eae6f.so.1.0.2k
pyarti.libs/libkrb5-6824148d.so.3.3
pyarti.libs/libkrb5support-f4e34ad2.so.0.1
pyarti.libs/libsqlite3-10f9d6e9.so.0.8.6
pyarti.libs/libcom_err-2abe824b.so.2.1
pyarti.libs/libkeyutils-dfe70bd6.so.1.5
pyarti.libs/libgssapi_krb5-497db0c6.so.2.2
pyarti.libs/libcrypto-19957f5b.so.1.0.2k
pyarti.libs/libselinux-0922c95c.so.1
pyarti.libs/libk5crypto-b1f99d5c.so.3.1
pyarti.libs/libpcre-9513aab5.so.1.2.0
