Metadata-Version: 2.1
Name: pyarti
Version: 0.0.2
Author-email: Kushal Das <mail@kushaldas.in>
Project-URL: Homepage, https://github.com/kushaldas/pyarti
Project-URL: Bug Tracker, https://github.com/kushaldas/pyarti/issues
Classifier: Development Status :: 3 - Alpha
Classifier: License :: OSI Approved :: MIT License
Classifier: Programming Language :: Rust
Classifier: Programming Language :: Python
Classifier: Programming Language :: Python :: 3 :: Only
Classifier: Programming Language :: Python :: 3.8
Classifier: Programming Language :: Python :: 3.9
Classifier: Programming Language :: Python :: 3.10
Classifier: Programming Language :: Python :: Implementation :: CPython
Classifier: Topic :: Software Development :: Libraries
Classifier: Topic :: Software Development :: Libraries :: Python Modules
Requires-Python: >=3.8
License-File: LICENSE
Requires-Dist: httpx
Requires-Dist: httpx-socks
Requires-Dist: pexpect
